dictiopy/__init__.py
dictiopy/dictio.py
dictiopy-0.2.0.dist-info/METADATA
dictiopy-0.2.0.dist-info/WHEEL
dictiopy-0.2.0.dist-info/entry_points.txt
dictiopy-0.2.0.dist-info/licenses/LICENSE
dictiopy-0.2.0.dist-info/RECORD
