Metadata-Version: 2.1
Name: dictiopy
Version: 0.2.0
Summary: A cli english dictionary
Author-email: Chen Yu-Qiao <chenyqmy@gmail.com>
License-File: LICENSE
Classifier: License :: OSI Approved :: MIT License
Classifier: Operating System :: OS Independent
Classifier: Programming Language :: Python :: 3
Requires-Python: >=3.7
Requires-Dist: click
Requires-Dist: requests
